pourewa/OrthancRestToolbox.py
pourewa/POUREWA.conf
pourewa/__init__.py
pourewa/helpers.py
pourewa/pdf2dicom.py
pourewa/pourewa.py
pourewa-0.1.1.dist-info/licenses/LICENSE
pourewa-0.1.1.dist-info/METADATA
pourewa-0.1.1.dist-info/WHEEL
pourewa-0.1.1.dist-info/entry_points.txt
pourewa-0.1.1.dist-info/top_level.txt
pourewa-0.1.1.dist-info/RECORD
