Metadata-Version: 2.4
Name: pourewa
Version: 0.1.1
Summary: A commandline tool for managing Orthanc DICOM servers
Home-page: https://github.com/fraser29/pourewa
Author: Fraser Callaghan
Author-email: callaghan.fm@gmail.com
Classifier: Programming Language :: Python :: 3
Classifier: License :: OSI Approved :: GNU General Public License v3 (GPLv3)
Classifier: Operating System :: OS Independent
Classifier: Development Status :: 3 - Alpha
Classifier: Intended Audience :: Science/Research
Classifier: Topic :: Scientific/Engineering :: Medical Science Apps.
Requires-Python: >=3.6
License-File: LICENSE
Requires-Dist: httplib2
Requires-Dist: pydicom
Dynamic: author
Dynamic: author-email
Dynamic: classifier
Dynamic: description
Dynamic: description-content-type
Dynamic: home-page
Dynamic: license-file
Dynamic: requires-dist
Dynamic: requires-python
Dynamic: summary
